<?xml version="1.0" encoding="utf-8"?>
<clothing-items>
 <clothing>
  <id>
   640660224
  </id>
  <name>
   New Balance Jacket P-6455
  </name>
  <category>
   Jacket
  </category>
  <size>
   XXL
  </size>
  <color>
   Желтый
  </color>
  <material>
   Вискоза
  </material>
  <price>
   662358
  </price>
  <rating>
   4.34
  </rating>
  <reviews>
   873383
  </reviews>
  <new>
   -
  </new>
 </clothing>
 <clothing>
  <id>
   723610030
  </id>
  <name>
   Brooks Umbrellas K-6851
  </name>
  <category>
   Umbrellas
  </category>
  <size>
   M
  </size>
  <color>
   Синий
  </color>
  <material>
   Кожа
  </material>
  <price>
   582364
  </price>
  <rating>
   4.57
  </rating>
  <reviews>
   638479
  </reviews>
  <new>
   -
  </new>
  <exclusive>
   no
  </exclusive>
 </clothing>
 <clothing>
  <id>
   543900561
  </id>
  <name>
   DC Shoes F-3684
  </name>
  <category>
   Shoes
  </category>
  <size>
   XXL
  </size>
  <color>
   Голубой
  </color>
  <material>
   Полиэстер
  </material>
  <price>
   173665
  </price>
  <rating>
   3.38
  </rating>
  <reviews>
   558782
  </reviews>
  <exclusive>
   yes
  </exclusive>
 </clothing>
 <clothing>
  <id>
   295981084
  </id>
  <name>
   Addidas Handbags Q-4573
  </name>
  <category>
   Handbags
  </category>
  <size>
   L
  </size>
  <color>
   Зеленый
  </color>
  <material>
   Нейлон
  </material>
  <price>
   276118
  </price>
  <rating>
   4.29
  </rating>
  <reviews>
   392745
  </reviews>
  <exclusive>
   no
  </exclusive>
 </clothing>
 <clothing>
  <id>
   250796161
  </id>
  <name>
   Under Armour Pants M-5255
  </name>
  <category>
   Pants
  </category>
  <size>
   M
  </size>
  <color>
   Синий
  </color>
  <material>
   Нейлон
  </material>
  <price>
   445577
  </price>
  <rating>
   3.02
  </rating>
  <reviews>
   126148
  </reviews>
  <new>
   +
  </new>
  <sporty>
   yes
  </sporty>
 </clothing>
 <clothing>
  <id>
   139578547
  </id>
  <name>
   Adidas Jacket U-4419
  </name>
  <category>
   Jacket
  </category>
  <size>
   L
  </size>
  <color>
   Оранжевый
  </color>
  <material>
   Кожа
  </material>
  <price>
   795254
  </price>
  <rating>
   1.89
  </rating>
  <reviews>
   757500
  </reviews>
  <new>
   -
  </new>
  <exclusive>
   no
  </exclusive>
 </clothing>
 <clothing>
  <id>
   794963913
  </id>
  <name>
   PleinSport Dress Q-8190
  </name>
  <category>
   Dress
  </category>
  <size>
   S
  </size>
  <color>
   Синий
  </color>
  <material>
   Кожа
  </material>
  <price>
   447812
  </price>
  <rating>
   3.71
  </rating>
  <reviews>
   94625
  </reviews>
  <sporty>
   no
  </sporty>
 </clothing>
 <clothing>
  <id>
   680481838
  </id>
  <name>
   Reebok Belts Q-4884
  </name>
  <category>
   Belts
  </category>
  <size>
   M
  </size>
  <color>
   Фиолетовый
  </color>
  <material>
   Хлопок
  </material>
  <price>
   479216
  </price>
  <rating>
   3.9
  </rating>
  <reviews>
   411829
  </reviews>
  <new>
   +
  </new>
  <exclusive>
   no
  </exclusive>
 </clothing>
 <clothing>
  <id>
   236076289
  </id>
  <name>
   Lacoste Blouse O-9110
  </name>
  <category>
   Blouse
  </category>
  <size>
   M
  </size>
  <color>
   Красный
  </color>
  <material>
   Лен
  </material>
  <price>
   751312
  </price>
  <rating>
   3.4
  </rating>
  <reviews>
   136704
  </reviews>
  <new>
   -
  </new>
  <exclusive>
   yes
  </exclusive>
  <sporty>
   no
  </sporty>
 </clothing>
 <clothing>
  <id>
   820036425
  </id>
  <name>
   Lacoste Handbags X-7348
  </name>
  <category>
   Handbags
  </category>
  <size>
   XL
  </size>
  <color>
   Фиолетовый
  </color>
  <material>
   Нейлон
  </material>
  <price>
   212432
  </price>
  <rating>
   3.17
  </rating>
  <reviews>
   67945
  </reviews>
  <new>
   -
  </new>
 </clothing>
 <clothing>
  <id>
   364723367
  </id>
  <name>
   Nike Handbags X-5095
  </name>
  <category>
   Handbags
  </category>
  <size>
   XL
  </size>
  <color>
   Фиолетовый
  </color>
  <material>
   Вискоза
  </material>
  <price>
   284021
  </price>
  <rating>
   1.43
  </rating>
  <reviews>
   56369
  </reviews>
  <new>
   -
  </new>
  <sporty>
   no
  </sporty>
 </clothing>
 <clothing>
  <id>
   533351607
  </id>
  <name>
   Reebok Skirt P-2732
  </name>
  <category>
   Skirt
  </category>
  <size>
   L
  </size>
  <color>
   Зеленый
  </color>
  <material>
   Полиэстер
  </material>
  <price>
   845947
  </price>
  <rating>
   3.63
  </rating>
  <reviews>
   967763
  </reviews>
  <exclusive>
   no
  </exclusive>
 </clothing>
 <clothing>
  <id>
   468079429
  </id>
  <name>
   Lacoste Shoes M-9179
  </name>
  <category>
   Shoes
  </category>
  <size>
   S
  </size>
  <color>
   Фиолетовый
  </color>
  <material>
   Лен
  </material>
  <price>
   631107
  </price>
  <rating>
   1.34
  </rating>
  <reviews>
   123006
  </reviews>
  <new>
   -
  </new>
  <sporty>
   no
  </sporty>
 </clothing>
 <clothing>
  <id>
   813036208
  </id>
  <name>
   Ellesse T-shirt O-3419
  </name>
  <category>
   T-shirt
  </category>
  <size>
   XL
  </size>
  <color>
   Фиолетовый
  </color>
  <material>
   Вискоза
  </material>
  <price>
   845508
  </price>
  <rating>
   1.68
  </rating>
  <reviews>
   948952
  </reviews>
  <sporty>
   no
  </sporty>
 </clothing>
 <clothing>
  <id>
   776687592
  </id>
  <name>
   Puma Hat I-8047
  </name>
  <category>
   Hat
  </category>
  <size>
   M
  </size>
  <color>
   Зеленый
  </color>
  <material>
   Кожа
  </material>
  <price>
   567292
  </price>
  <rating>
   1.77
  </rating>
  <reviews>
   641491
  </reviews>
  <new>
   -
  </new>
  <exclusive>
   yes
  </exclusive>
 </clothing>
 <clothing>
  <id>
   326492715
  </id>
  <name>
   Addidas Shoes C-8854
  </name>
  <category>
   Shoes
  </category>
  <size>
   L
  </size>
  <color>
   Голубой
  </color>
  <material>
   Кожа
  </material>
  <price>
   732583
  </price>
  <rating>
   2.62
  </rating>
  <reviews>
   197946
  </reviews>
 </clothing>
 <clothing>
  <id>
   365136822
  </id>
  <name>
   DC Belts Y-5479
  </name>
  <category>
   Belts
  </category>
  <size>
   L
  </size>
  <color>
   Синий
  </color>
  <material>
   Полиэстер
  </material>
  <price>
   689145
  </price>
  <rating>
   2.37
  </rating>
  <reviews>
   89634
  </reviews>
  <sporty>
   no
  </sporty>
 </clothing>
 <clothing>
  <id>
   664658248
  </id>
  <name>
   DC Shirt Q-4438
  </name>
  <category>
   Shirt
  </category>
  <size>
   XL
  </size>
  <color>
   Синий
  </color>
  <material>
   Вискоза
  </material>
  <price>
   185170
  </price>
  <rating>
   1.26
  </rating>
  <reviews>
   455571
  </reviews>
  <new>
   -
  </new>
  <exclusive>
   no
  </exclusive>
 </clothing>
 <clothing>
  <id>
   807142016
  </id>
  <name>
   DC Sweater I-7239
  </name>
  <category>
   Sweater
  </category>
  <size>
   S
  </size>
  <color>
   Зеленый
  </color>
  <material>
   Шерсть
  </material>
  <price>
   429377
  </price>
  <rating>
   2.15
  </rating>
  <reviews>
   217768
  </reviews>
  <new>
   -
  </new>
  <exclusive>
   yes
  </exclusive>
  <sporty>
   no
  </sporty>
 </clothing>
 <clothing>
  <id>
   715167034
  </id>
  <name>
   Adidas Skirt I-2948
  </name>
  <category>
   Skirt
  </category>
  <size>
   XXL
  </size>
  <color>
   Красный
  </color>
  <material>
   Вискоза
  </material>
  <price>
   920191
  </price>
  <rating>
   4.59
  </rating>
  <reviews>
   874016
  </reviews>
  <sporty>
   no
  </sporty>
 </clothing>
 <clothing>
  <id>
   523847552
  </id>
  <name>
   Asics Hat M-5854
  </name>
  <category>
   Hat
  </category>
  <size>
   S
  </size>
  <color>
   Красный
  </color>
  <material>
   Шелк
  </material>
  <price>
   706010
  </price>
  <rating>
   1.8
  </rating>
  <reviews>
   70105
  </reviews>
  <new>
   -
  </new>
 </clothing>
 <clothing>
  <id>
   420044601
  </id>
  <name>
   Reebok Dress F-9055
  </name>
  <category>
   Dress
  </category>
  <size>
   L
  </size>
  <color>
   Красный
  </color>
  <material>
   Хлопок
  </material>
  <price>
   430413
  </price>
  <rating>
   1.38
  </rating>
  <reviews>
   589032
  </reviews>
  <new>
   -
  </new>
  <exclusive>
   no
  </exclusive>
  <sporty>
   no
  </sporty>
 </clothing>
 <clothing>
  <id>
   345512035
  </id>
  <name>
   Reebok Dress X-8513
  </name>
  <category>
   Dress
  </category>
  <size>
   M
  </size>
  <color>
   Фиолетовый
  </color>
  <material>
   Шерсть
  </material>
  <price>
   861903
  </price>
  <rating>
   2.46
  </rating>
  <reviews>
   635279
  </reviews>
  <exclusive>
   no
  </exclusive>
 </clothing>
 <clothing>
  <id>
   744497001
  </id>
  <name>
   Brooks T-shirt W-8794
  </name>
  <category>
   T-shirt
  </category>
  <size>
   M
  </size>
  <color>
   Желтый
  </color>
  <material>
   Лен
  </material>
  <price>
   836204
  </price>
  <rating>
   4.03
  </rating>
  <reviews>
   90848
  </reviews>
  <sporty>
   no
  </sporty>
 </clothing>
 <clothing>
  <id>
   459228545
  </id>
  <name>
   New Balance Jacket G-3893
  </name>
  <category>
   Jacket
  </category>
  <size>
   XL
  </size>
  <color>
   Желтый
  </color>
  <material>
   Нейлон
  </material>
  <price>
   846788
  </price>
  <rating>
   3.8
  </rating>
  <reviews>
   877933
  </reviews>
  <new>
   -
  </new>
  <sporty>
   no
  </sporty>
 </clothing>
 <clothing>
  <id>
   451652150
  </id>
  <name>
   Puma Shoes U-8051
  </name>
  <category>
   Shoes
  </category>
  <size>
   L
  </size>
  <color>
   Красный
  </color>
  <material>
   Шерсть
  </material>
  <price>
   972971
  </price>
  <rating>
   2.98
  </rating>
  <reviews>
   360534
  </reviews>
  <sporty>
   no
  </sporty>
 </clothing>
 <clothing>
  <id>
   667137674
  </id>
  <name>
   Nike Skirt E-2966
  </name>
  <category>
   Skirt
  </category>
  <size>
   M
  </size>
  <color>
   Синий
  </color>
  <material>
   Шелк
  </material>
  <price>
   882771
  </price>
  <rating>
   3.64
  </rating>
  <reviews>
   871007
  </reviews>
  <sporty>
   yes
  </sporty>
 </clothing>
 <clothing>
  <id>
   284693651
  </id>
  <name>
   Under Armour Pants T-2679
  </name>
  <category>
   Pants
  </category>
  <size>
   XXL
  </size>
  <color>
   Желтый
  </color>
  <material>
   Нейлон
  </material>
  <price>
   578199
  </price>
  <rating>
   2.67
  </rating>
  <reviews>
   225540
  </reviews>
  <sporty>
   no
  </sporty>
 </clothing>
 <clothing>
  <id>
   947709798
  </id>
  <name>
   DC T-shirt B-5983
  </name>
  <category>
   T-shirt
  </category>
  <size>
   S
  </size>
  <color>
   Синий
  </color>
  <material>
   Полиэстер
  </material>
  <price>
   465174
  </price>
  <rating>
   4.19
  </rating>
  <reviews>
   603688
  </reviews>
  <exclusive>
   yes
  </exclusive>
  <sporty>
   yes
  </sporty>
 </clothing>
 <clothing>
  <id>
   732028483
  </id>
  <name>
   Addidas Shoes X-4555
  </name>
  <category>
   Shoes
  </category>
  <size>
   S
  </size>
  <color>
   Зеленый
  </color>
  <material>
   Шелк
  </material>
  <price>
   696359
  </price>
  <rating>
   4.8
  </rating>
  <reviews>
   351399
  </reviews>
  <new>
   +
  </new>
  <exclusive>
   no
  </exclusive>
  <sporty>
   no
  </sporty>
 </clothing>
 <clothing>
  <id>
   609543131
  </id>
  <name>
   Brooks Hat O-8962
  </name>
  <category>
   Hat
  </category>
  <size>
   XXL
  </size>
  <color>
   Синий
  </color>
  <material>
   Лен
  </material>
  <price>
   782114
  </price>
  <rating>
   3.37
  </rating>
  <reviews>
   444456
  </reviews>
  <new>
   -
  </new>
 </clothing>
 <clothing>
  <id>
   296003219
  </id>
  <name>
   Vans Gloves D-6054
  </name>
  <category>
   Gloves
  </category>
  <size>
   XL
  </size>
  <color>
   Красный
  </color>
  <material>
   Шелк
  </material>
  <price>
   455216
  </price>
  <rating>
   2.46
  </rating>
  <reviews>
   622537
  </reviews>
  <new>
   -
  </new>
  <exclusive>
   yes
  </exclusive>
 </clothing>
 <clothing>
  <id>
   793076206
  </id>
  <name>
   Lacoste Jacket B-4757
  </name>
  <category>
   Jacket
  </category>
  <size>
   M
  </size>
  <color>
   Фиолетовый
  </color>
  <material>
   Лен
  </material>
  <price>
   159069
  </price>
  <rating>
   2.27
  </rating>
  <reviews>
   788760
  </reviews>
  <new>
   -
  </new>
  <exclusive>
   no
  </exclusive>
 </clothing>
 <clothing>
  <id>
   312434597
  </id>
  <name>
   DC Sweater N-9460
  </name>
  <category>
   Sweater
  </category>
  <size>
   S
  </size>
  <color>
   Зеленый
  </color>
  <material>
   Лен
  </material>
  <price>
   590396
  </price>
  <rating>
   2.37
  </rating>
  <reviews>
   520421
  </reviews>
  <exclusive>
   no
  </exclusive>
  <sporty>
   yes
  </sporty>
 </clothing>
 <clothing>
  <id>
   331035066
  </id>
  <name>
   Adidas Dress M-7933
  </name>
  <category>
   Dress
  </category>
  <size>
   XL
  </size>
  <color>
   Фиолетовый
  </color>
  <material>
   Вискоза
  </material>
  <price>
   377973
  </price>
  <rating>
   1.15
  </rating>
  <reviews>
   867714
  </reviews>
 </clothing>
 <clothing>
  <id>
   198462526
  </id>
  <name>
   Fila Belts K-2412
  </name>
  <category>
   Belts
  </category>
  <size>
   S
  </size>
  <color>
   Оранжевый
  </color>
  <material>
   Шерсть
  </material>
  <price>
   138209
  </price>
  <rating>
   2.91
  </rating>
  <reviews>
   486522
  </reviews>
  <exclusive>
   no
  </exclusive>
  <sporty>
   no
  </sporty>
 </clothing>
 <clothing>
  <id>
   641905268
  </id>
  <name>
   Asics Belts S-6626
  </name>
  <category>
   Belts
  </category>
  <size>
   S
  </size>
  <color>
   Желтый
  </color>
  <material>
   Кожа
  </material>
  <price>
   297724
  </price>
  <rating>
   4.77
  </rating>
  <reviews>
   372560
  </reviews>
  <new>
   +
  </new>
  <exclusive>
   no
  </exclusive>
  <sporty>
   yes
  </sporty>
 </clothing>
 <clothing>
  <id>
   367458611
  </id>
  <name>
   Nike Gloves X-9062
  </name>
  <category>
   Gloves
  </category>
  <size>
   XXL
  </size>
  <color>
   Желтый
  </color>
  <material>
   Полиэстер
  </material>
  <price>
   548285
  </price>
  <rating>
   3.82
  </rating>
  <reviews>
   14381
  </reviews>
  <exclusive>
   yes
  </exclusive>
  <sporty>
   no
  </sporty>
 </clothing>
 <clothing>
  <id>
   284554064
  </id>
  <name>
   DC Handbags S-1369
  </name>
  <category>
   Handbags
  </category>
  <size>
   S
  </size>
  <color>
   Синий
  </color>
  <material>
   Хлопок
  </material>
  <price>
   559063
  </price>
  <rating>
   3.3
  </rating>
  <reviews>
   36432
  </reviews>
  <new>
   +
  </new>
  <sporty>
   no
  </sporty>
 </clothing>
 <clothing>
  <id>
   952122159
  </id>
  <name>
   Under Armour Jeans D-8958
  </name>
  <category>
   Jeans
  </category>
  <size>
   XXL
  </size>
  <color>
   Синий
  </color>
  <material>
   Шелк
  </material>
  <price>
   262306
  </price>
  <rating>
   3.17
  </rating>
  <reviews>
   637332
  </reviews>
  <sporty>
   no
  </sporty>
 </clothing>
 <clothing>
  <id>
   565353661
  </id>
  <name>
   Lacoste Shirt E-9705
  </name>
  <category>
   Shirt
  </category>
  <size>
   M
  </size>
  <color>
   Оранжевый
  </color>
  <material>
   Шерсть
  </material>
  <price>
   257393
  </price>
  <rating>
   3.11
  </rating>
  <reviews>
   817285
  </reviews>
  <new>
   +
  </new>
 </clothing>
 <clothing>
  <id>
   873963827
  </id>
  <name>
   Brooks Jacket X-3884
  </name>
  <category>
   Jacket
  </category>
  <size>
   XL
  </size>
  <color>
   Голубой
  </color>
  <material>
   Полиэстер
  </material>
  <price>
   360724
  </price>
  <rating>
   1.24
  </rating>
  <reviews>
   117213
  </reviews>
  <new>
   +
  </new>
  <exclusive>
   no
  </exclusive>
  <sporty>
   yes
  </sporty>
 </clothing>
 <clothing>
  <id>
   573570140
  </id>
  <name>
   Asics Hat F-5190
  </name>
  <category>
   Hat
  </category>
  <size>
   M
  </size>
  <color>
   Голубой
  </color>
  <material>
   Лен
  </material>
  <price>
   647936
  </price>
  <rating>
   2.72
  </rating>
  <reviews>
   76647
  </reviews>
  <sporty>
   no
  </sporty>
 </clothing>
 <clothing>
  <id>
   356390488
  </id>
  <name>
   New Balance Pants L-6187
  </name>
  <category>
   Pants
  </category>
  <size>
   XXL
  </size>
  <color>
   Желтый
  </color>
  <material>
   Шелк
  </material>
  <price>
   645666
  </price>
  <rating>
   3.76
  </rating>
  <reviews>
   194106
  </reviews>
  <new>
   -
  </new>
  <exclusive>
   no
  </exclusive>
  <sporty>
   no
  </sporty>
 </clothing>
 <clothing>
  <id>
   351045783
  </id>
  <name>
   Brooks Jeans N-4624
  </name>
  <category>
   Jeans
  </category>
  <size>
   L
  </size>
  <color>
   Оранжевый
  </color>
  <material>
   Хлопок
  </material>
  <price>
   261342
  </price>
  <rating>
   4.35
  </rating>
  <reviews>
   997968
  </reviews>
  <new>
   -
  </new>
  <exclusive>
   yes
  </exclusive>
  <sporty>
   yes
  </sporty>
 </clothing>
 <clothing>
  <id>
   316151305
  </id>
  <name>
   Puma T-shirt C-4156
  </name>
  <category>
   T-shirt
  </category>
  <size>
   XL
  </size>
  <color>
   Желтый
  </color>
  <material>
   Хлопок
  </material>
  <price>
   351558
  </price>
  <rating>
   1.21
  </rating>
  <reviews>
   67346
  </reviews>
  <sporty>
   no
  </sporty>
 </clothing>
 <clothing>
  <id>
   637243186
  </id>
  <name>
   Converse Jacket V-1976
  </name>
  <category>
   Jacket
  </category>
  <size>
   L
  </size>
  <color>
   Желтый
  </color>
  <material>
   Лен
  </material>
  <price>
   285377
  </price>
  <rating>
   3.96
  </rating>
  <reviews>
   416535
  </reviews>
  <new>
   -
  </new>
  <exclusive>
   yes
  </exclusive>
 </clothing>
 <clothing>
  <id>
   212705236
  </id>
  <name>
   Nike Shoes V-1485
  </name>
  <category>
   Shoes
  </category>
  <size>
   XXL
  </size>
  <color>
   Желтый
  </color>
  <material>
   Хлопок
  </material>
  <price>
   260884
  </price>
  <rating>
   1.06
  </rating>
  <reviews>
   606850
  </reviews>
  <exclusive>
   no
  </exclusive>
 </clothing>
 <clothing>
  <id>
   531099131
  </id>
  <name>
   Puma Dress J-8434
  </name>
  <category>
   Dress
  </category>
  <size>
   L
  </size>
  <color>
   Желтый
  </color>
  <material>
   Кожа
  </material>
  <price>
   845320
  </price>
  <rating>
   1.34
  </rating>
  <reviews>
   234016
  </reviews>
  <exclusive>
   no
  </exclusive>
 </clothing>
</clothing-items>
